setup.py
bin/grit
grit/__init__.py
grit.egg-info/PKG-INFO
grit.egg-info/SOURCES.txt
grit.egg-info/dependency_links.txt
grit.egg-info/not-zip-safe
grit.egg-info/top_level.txt
grit/cfg/__init__.py
grit/cfg/cfg.py
grit/cmd/__init__.py
grit/cmd/cli.py
grit/cmd/cmd.py
grit/exc/__init__.py
grit/exc/exc.py
grit/log/__init__.py
grit/log/log.py
grit/repo/__init__.py
grit/repo/base.py
grit/repo/local.py
grit/repo/proxy.py
grit/repo/version.py
grit/server/__init__.py
grit/server/git_http_backend.py
grit/server/handler.py
grit/server/server.py
grit/server/subprocessio.py
grit/server/cherrypy/__init__.py
grit/server/cherrypy/ssl_builtin.py
grit/server/cherrypy/ssl_pyopenssl.py
grit/util/__init__.py
grit/util/util.py
test/test.py