Metadata-Version: 1.0
Name: grit
Version: 0.1
Summary: Grit is a simple git repo manager with limited remote object proxying, a http back-end and simple cli.
Home-page: http://www.github.com/rsgalloway/grit
Author: Ryan Galloway
Author-email: ryan@rsgalloway.com
License: New BSD License
Keywords: git repo manager remote object proxy
Platform: OS Independent
Classifier: Development Status :: 2 - Pre-Alpha
Classifier: Topic :: Utilities
Classifier: License :: OSI Approved :: BSD License
